diskchef/__init__.py
diskchef/chemistry/__init__.py
diskchef/chemistry/abundances.py
diskchef/chemistry/base.py
diskchef/engine/__init__.py
diskchef/engine/ctable.py
diskchef/engine/exceptions.py
diskchef/engine/logger.py
diskchef/physics/__init__.py
diskchef/physics/base.py
diskchef/physics/parametrized.py
diskchef-0.1.dist-info/LICENSE
diskchef-0.1.dist-info/METADATA
diskchef-0.1.dist-info/WHEEL
diskchef-0.1.dist-info/top_level.txt
diskchef-0.1.dist-info/RECORD
