Metadata-Version: 2.1
Name: diskchef
Version: 0.1
Summary: Tool to retrieve chemical and physical parameters out of submm observations
Home-page: https://gitlab.com/SmirnGreg/diskchef
Author: Grigorii V. Smirnov-Pinchukov
Author-email: smirnov@mpia.de
License: (c) authors
Platform: UNKNOWN
